<?xml version="1.0" encoding="UTF-8"?>
<!-- job list for ds-sim, 28-Feb, 2023 @ MQ - client-server -->
<jobs>
	<type name="short" minRunTime="1" maxRunTime="300" populationRate="30" />
	<type name="medium" minRunTime="301" maxRunTime="1800" populationRate="50" />
	<type name="long" minRunTime="1801" maxRunTime="100000" populationRate="20" />
	<job id="0" type="long" submitTime="37" estRunTime="7573" cores="3" memory="700" disk="3800" />
	<job id="1" type="medium" submitTime="60" estRunTime="2025" cores="2" memory="1500" disk="2900" />
	<job id="2" type="long" submitTime="96" estRunTime="21943" cores="2" memory="1500" disk="2100" />
	<job id="3" type="long" submitTime="101" estRunTime="29081" cores="4" memory="1800" disk="5100" />
	<job id="4" type="short" submitTime="137" estRunTime="111" cores="1" memory="100" disk="2000" />
	<job id="5" type="medium" submitTime="141" estRunTime="80" cores="3" memory="2700" disk="2600" />
	<job id="6" type="long" submitTime="163" estRunTime="36990" cores="4" memory="4000" disk="7600" />
	<job id="7" type="medium" submitTime="190" estRunTime="442" cores="2" memory="500" disk="2100" />
	<job id="8" type="medium" submitTime="214" estRunTime="926" cores="1" memory="100" disk="800" />
	<job id="9" type="medium" submitTime="328" estRunTime="2010" cores="2" memory="600" disk="1500" />
	<job id="10" type="short" submitTime="535" estRunTime="380" cores="1" memory="200" disk="100" />
	<job id="11" type="short" submitTime="577" estRunTime="114" cores="1" memory="700" disk="400" />
	<job id="12" type="medium" submitTime="669" estRunTime="1682" cores="3" memory="1900" disk="500" />
	<job id="13" type="medium" submitTime="814" estRunTime="340" cores="4" memory="3500" disk="3900" />
	<job id="14" type="long" submitTime="1219" estRunTime="36028" cores="8" memory="4700" disk="5900" />
	<job id="15" type="medium" submitTime="2451" estRunTime="692" cores="1" memory="900" disk="2800" />
	<job id="16" type="long" submitTime="2587" estRunTime="58799" cores="2" memory="300" disk="2500" />
	<job id="17" type="medium" submitTime="3461" estRunTime="2220" cores="2" memory="1600" disk="3500" />
	<job id="18" type="medium" submitTime="4828" estRunTime="2382" cores="4" memory="800" disk="1100" />
	<job id="19" type="long" submitTime="6122" estRunTime="53123" cores="7" memory="2900" disk="5900" />
	<job id="20" type="medium" submitTime="23749" estRunTime="990" cores="1" memory="500" disk="1600" />
	<job id="21" type="medium" submitTime="25069" estRunTime="319" cores="4" memory="400" disk="2000" />
	<job id="22" type="long" submitTime="25796" estRunTime="136124" cores="3" memory="3000" disk="2200" />
	<job id="23" type="short" submitTime="25861" estRunTime="165" cores="1" memory="800" disk="1400" />
	<job id="24" type="medium" submitTime="26544" estRunTime="1019" cores="4" memory="900" disk="3600" />
	<job id="25" type="medium" submitTime="27202" estRunTime="646" cores="4" memory="3400" disk="4400" />
	<job id="26" type="medium" submitTime="27916" estRunTime="1575" cores="3" memory="3200" disk="3800" />
	<job id="27" type="medium" submitTime="28710" estRunTime="799" cores="3" memory="2100" disk="2500" />
	<job id="28" type="short" submitTime="29592" estRunTime="338" cores="1" memory="1900" disk="2500" />
	<job id="29" type="short" submitTime="30326" estRunTime="13" cores="4" memory="4300" disk="6000" />
	<job id="30" type="medium" submitTime="31035" estRunTime="666" cores="2" memory="1300" disk="1200" />
	<job id="31" type="medium" submitTime="31657" estRunTime="1378" cores="3" memory="1400" disk="4100" />
	<job id="32" type="short" submitTime="31975" estRunTime="233" cores="1" memory="500" disk="900" />
	<job id="33" type="medium" submitTime="32631" estRunTime="1426" cores="1" memory="400" disk="1000" />
	<job id="34" type="medium" submitTime="33042" estRunTime="1815" cores="1" memory="800" disk="1700" />
	<job id="35" type="long" submitTime="33433" estRunTime="10040" cores="3" memory="3000" disk="2500" />
	<job id="36" type="short" submitTime="33736" estRunTime="214" cores="4" memory="3300" disk="7900" />
	<job id="37" type="long" submitTime="34458" estRunTime="11477" cores="1" memory="800" disk="400" />
	<job id="38" type="medium" submitTime="34955" estRunTime="2848" cores="4" memory="900" disk="2400" />
	<job id="39" type="medium" submitTime="35279" estRunTime="1493" cores="3" memory="500" disk="2000" />
	<job id="40" type="short" submitTime="36905" estRunTime="58" cores="1" memory="800" disk="600" />
	<job id="41" type="short" submitTime="37325" estRunTime="113" cores="1" memory="100" disk="1000" />
	<job id="42" type="short" submitTime="38100" estRunTime="367" cores="1" memory="200" disk="1500" />
	<job id="43" type="short" submitTime="38250" estRunTime="1" cores="7" memory="5500" disk="3800" />
	<job id="44" type="short" submitTime="38937" estRunTime="155" cores="4" memory="2500" disk="900" />
	<job id="45" type="long" submitTime="39319" estRunTime="85240" cores="1" memory="300" disk="1700" />
	<job id="46" type="medium" submitTime="39417" estRunTime="60" cores="4" memory="1200" disk="3600" />
	<job id="47" type="medium" submitTime="39523" estRunTime="1352" cores="4" memory="1000" disk="4500" />
	<job id="48" type="short" submitTime="39611" estRunTime="257" cores="2" memory="1500" disk="2700" />
	<job id="49" type="short" submitTime="39976" estRunTime="2" cores="3" memory="300" disk="4000" />
	<job id="50" type="long" submitTime="40417" estRunTime="133432" cores="3" memory="2700" disk="3300" />
	<job id="51" type="medium" submitTime="40643" estRunTime="2435" cores="2" memory="1800" disk="900" />
	<job id="52" type="short" submitTime="41185" estRunTime="58" cores="1" memory="1000" disk="1400" />
	<job id="53" type="medium" submitTime="41575" estRunTime="748" cores="1" memory="300" disk="200" />
	<job id="54" type="medium" submitTime="42066" estRunTime="1384" cores="4" memory="4000" disk="2200" />
	<job id="55" type="medium" submitTime="42245" estRunTime="1978" cores="5" memory="2800" disk="4000" />
	<job id="56" type="short" submitTime="43727" estRunTime="293" cores="1" memory="1000" disk="100" />
	<job id="57" type="medium" submitTime="44342" estRunTime="883" cores="1" memory="500" disk="300" />
	<job id="58" type="medium" submitTime="44815" estRunTime="1497" cores="1" memory="100" disk="600" />
	<job id="59" type="short" submitTime="45483" estRunTime="126" cores="3" memory="1900" disk="3600" />
	<job id="60" type="short" submitTime="45856" estRunTime="92" cores="1" memory="1000" disk="200" />
	<job id="61" type="medium" submitTime="46167" estRunTime="2446" cores="2" memory="2100" disk="1500" />
	<job id="62" type="medium" submitTime="46776" estRunTime="1950" cores="1" memory="1000" disk="1400" />
	<job id="63" type="long" submitTime="47163" estRunTime="175162" cores="4" memory="3800" disk="4500" />
	<job id="64" type="short" submitTime="47816" estRunTime="19" cores="3" memory="300" disk="1600" />
	<job id="65" type="short" submitTime="48429" estRunTime="154" cores="3" memory="2000" disk="6100" />
	<job id="66" type="medium" submitTime="48811" estRunTime="494" cores="2" memory="800" disk="2000" />
	<job id="67" type="long" submitTime="49191" estRunTime="96384" cores="4" memory="900" disk="2200" />
	<job id="68" type="long" submitTime="49339" estRunTime="14570" cores="3" memory="400" disk="1600" />
	<job id="69" type="short" submitTime="56951" estRunTime="115" cores="3" memory="300" disk="2100" />
	<job id="70" type="short" submitTime="57610" estRunTime="62" cores="4" memory="600" disk="2000" />
	<job id="71" type="medium" submitTime="57841" estRunTime="3090" cores="1" memory="800" disk="400" />
	<job id="72" type="short" submitTime="58306" estRunTime="59" cores="3" memory="1300" disk="1900" />
	<job id="73" type="medium" submitTime="58599" estRunTime="623" cores="2" memory="500" disk="2700" />
	<job id="74" type="medium" submitTime="58941" estRunTime="97" cores="1" memory="600" disk="900" />
	<job id="75" type="short" submitTime="59378" estRunTime="52" cores="3" memory="2600" disk="400" />
	<job id="76" type="short" submitTime="59759" estRunTime="28" cores="2" memory="1400" disk="300" />
	<job id="77" type="long" submitTime="59862" estRunTime="25515" cores="1" memory="200" disk="1800" />
	<job id="78" type="long" submitTime="60187" estRunTime="8353" cores="2" memory="1100" disk="2800" />
	<job id="79" type="short" submitTime="61027" estRunTime="323" cores="4" memory="4000" disk="1300" />
	<job id="80" type="long" submitTime="61661" estRunTime="98449" cores="4" memory="4000" disk="3200" />
	<job id="81" type="short" submitTime="97216" estRunTime="6" cores="2" memory="400" disk="1100" />
	<job id="82" type="short" submitTime="98359" estRunTime="148" cores="1" memory="100" disk="1600" />
	<job id="83" type="short" submitTime="98369" estRunTime="206" cores="2" memory="1400" disk="3700" />
	<job id="84" type="short" submitTime="98917" estRunTime="25" cores="4" memory="1100" disk="800" />
	<job id="85" type="short" submitTime="99124" estRunTime="10" cores="1" memory="300" disk="300" />
	<job id="86" type="short" submitTime="100170" estRunTime="35" cores="1" memory="600" disk="1100" />
	<job id="87" type="short" submitTime="100728" estRunTime="253" cores="1" memory="1000" disk="1600" />
	<job id="88" type="medium" submitTime="101839" estRunTime="1406" cores="4" memory="1000" disk="1900" />
	<job id="89" type="short" submitTime="101901" estRunTime="349" cores="8" memory="1400" disk="2300" />
	<job id="90" type="short" submitTime="103171" estRunTime="243" cores="3" memory="2900" disk="5300" />
	<job id="91" type="medium" submitTime="103271" estRunTime="865" cores="3" memory="1300" disk="3800" />
	<job id="92" type="long" submitTime="103516" estRunTime="41263" cores="2" memory="900" disk="2900" />
	<job id="93" type="long" submitTime="104122" estRunTime="64758" cores="3" memory="1200" disk="4700" />
	<job id="94" type="short" submitTime="105137" estRunTime="2" cores="6" memory="2700" disk="6900" />
	<job id="95" type="medium" submitTime="106168" estRunTime="661" cores="1" memory="500" disk="1900" />
	<job id="96" type="medium" submitTime="108635" estRunTime="1004" cores="1" memory="100" disk="1700" />
	<job id="97" type="long" submitTime="109720" estRunTime="95356" cores="3" memory="800" disk="300" />
	<job id="98" type="short" submitTime="127767" estRunTime="213" cores="1" memory="400" disk="300" />
	<job id="99" type="medium" submitTime="128791" estRunTime="1725" cores="2" memory="1300" disk="200" />
</jobs>
